topsis/__init__.py
topsis/__main__.py
topsis/topsis.py
topsis_nandini-0.1.11.dist-info/licenses/LICENSE.txt
topsis_nandini-0.1.11.dist-info/METADATA
topsis_nandini-0.1.11.dist-info/WHEEL
topsis_nandini-0.1.11.dist-info/entry_points.txt
topsis_nandini-0.1.11.dist-info/top_level.txt
topsis_nandini-0.1.11.dist-info/RECORD
