Metadata-Version: 2.4
Name: topsis-nandini
Version: 0.1.11
Summary: TOPSIS implementation for multi-criteria decision making
Author: Nandini Shekhar
Author-email: nandiniii.2404@gmail.com
Classifier: Programming Language :: Python :: 3
Classifier: License :: OSI Approved :: MIT License
License-File: LICENSE.txt
Requires-Dist: numpy
Requires-Dist: pandas
Dynamic: author
Dynamic: author-email
Dynamic: classifier
Dynamic: description
Dynamic: description-content-type
Dynamic: license-file
Dynamic: requires-dist
Dynamic: summary
